blossompy/__init__.py
blossompy/__main__.py
blossompy/main.py
blossompy/blossom/__init__.py
blossompy/blossom/main.py
blossompy/blossom/src/__init__.py
blossompy/blossom/src/config.py
blossompy/blossom/src/robot.py
blossompy/blossom/src/sequence.py
blossompy/blossom/src/sequencerobot.py
blossompy/blossom/src/split_seq.py
blossompy/blossom/src/text_interface.py
blossompy/src/__init__.py
blossompy/src/config.py
blossompy/src/robot.py
blossompy/src/sequence.py
blossompy/src/sequencerobot.py
blossompy/src/split_seq.py
blossompy/src/text_interface.py
blossompy/src/sequences/test/anger_sequence.json
blossompy/src/sequences/test/fear_sequence.json
blossompy/src/sequences/test/happy_sequence.json
blossompy/src/sequences/test/no_sequence.json
blossompy/src/sequences/test/reset_sequence.json
blossompy/src/sequences/test/sad_sequence.json
blossompy/src/sequences/test/yes_sequence.json
blossompy/src/sequences/woody/backstory_sequence.json
blossompy/src/sequences/woody/no_sequence.json
blossompy/src/sequences/woody/reset_sequence.json
blossompy/src/sequences/woody/yes_sequence.json
blossompy/src/sequences/woody/anger/anger_0_109_sequence.json
blossompy/src/sequences/woody/anger/anger_1_109_sequence.json
blossompy/src/sequences/woody/anger/anger_20181204_120338_sequence.json
blossompy/src/sequences/woody/anger/anger_20181204_121255_sequence.json
blossompy/src/sequences/woody/anger/anger_20181204_121739_sequence.json
blossompy/src/sequences/woody/anger/anger_20181204_122044_sequence.json
blossompy/src/sequences/woody/anger/anger_20181204_122642_sequence.json
blossompy/src/sequences/woody/anger/anger_20181204_123055_sequence.json
blossompy/src/sequences/woody/anger/anger_20181204_123101_sequence.json
blossompy/src/sequences/woody/anger/anger_20181204_123416_sequence.json
blossompy/src/sequences/woody/anger/anger_20181204_125506_sequence.json
blossompy/src/sequences/woody/anger/anger_20181204_130211_sequence.json
blossompy-1.1.0.dist-info/LICENSE
blossompy-1.1.0.dist-info/METADATA
blossompy-1.1.0.dist-info/WHEEL
blossompy-1.1.0.dist-info/top_level.txt
blossompy-1.1.0.dist-info/RECORD
