Metadata-Version: 2.1
Name: blossompy
Version: 1.1.0
Summary: Used to run and create basic commands for Human-Robot Interaction with the Blossom Robot
Home-page: https://github.com/riya-ranjan/blossom-public/tree/master/blossompy
Author: Riya Ranjan
Author-email: riya.ranjan.00@gmail.com
License: MIT
Platform: UNKNOWN
License-File: LICENSE
Requires-Dist: PyQt5
Requires-Dist: py-getch
Requires-Dist: getch
Requires-Dist: opencv-python (==4.3.0.38)
Requires-Dist: simpleaudio
Requires-Dist: PyYAML
Requires-Dist: flask-cors
Requires-Dist: prettytable
